fnal_column_analysis_tools/__init__.py
fnal_column_analysis_tools/util.py
fnal_column_analysis_tools/version.py
fnal_column_analysis_tools/analysis_objects/JaggedCandidateArray.py
fnal_column_analysis_tools/analysis_objects/__init__.py
fnal_column_analysis_tools/arrays/Builder.py
fnal_column_analysis_tools/arrays/__init__.py
fnal_column_analysis_tools/hist/__init__.py
fnal_column_analysis_tools/hist/export.py
fnal_column_analysis_tools/hist/hist_tools.py
fnal_column_analysis_tools/hist/plot.py
fnal_column_analysis_tools/jetmet_tools/FactorizedJetCorrector.py
fnal_column_analysis_tools/jetmet_tools/JetCorrectionUncertainty.py
fnal_column_analysis_tools/jetmet_tools/JetResolution.py
fnal_column_analysis_tools/jetmet_tools/JetResolutionScaleFactor.py
fnal_column_analysis_tools/jetmet_tools/JetTransformer.py
fnal_column_analysis_tools/jetmet_tools/__init__.py
fnal_column_analysis_tools/lookup_tools/__init__.py
fnal_column_analysis_tools/lookup_tools/csv_converters.py
fnal_column_analysis_tools/lookup_tools/dense_evaluated_lookup.py
fnal_column_analysis_tools/lookup_tools/dense_lookup.py
fnal_column_analysis_tools/lookup_tools/evaluator.py
fnal_column_analysis_tools/lookup_tools/extractor.py
fnal_column_analysis_tools/lookup_tools/jec_uncertainty_lookup.py
fnal_column_analysis_tools/lookup_tools/jersf_lookup.py
fnal_column_analysis_tools/lookup_tools/jme_standard_function.py
fnal_column_analysis_tools/lookup_tools/json_converters.py
fnal_column_analysis_tools/lookup_tools/lookup_base.py
fnal_column_analysis_tools/lookup_tools/root_converters.py
fnal_column_analysis_tools/lookup_tools/txt_converters.py
fnal_column_analysis_tools/lumi_tools/__init__.py
fnal_column_analysis_tools/processor/__init__.py
fnal_column_analysis_tools/processor/accumulator.py
fnal_column_analysis_tools/processor/dataframe.py
fnal_column_analysis_tools/processor/executor.py
fnal_column_analysis_tools/processor/helpers.py
fnal_column_analysis_tools/processor/processor.py
fnal_column_analysis_tools-0.4.23.dist-info/LICENSE
fnal_column_analysis_tools-0.4.23.dist-info/METADATA
fnal_column_analysis_tools-0.4.23.dist-info/WHEEL
fnal_column_analysis_tools-0.4.23.dist-info/top_level.txt
fnal_column_analysis_tools-0.4.23.dist-info/RECORD
