Metadata-Version: 2.1
Name: fnal-column-analysis-tools
Version: 0.4.23
Summary: Tools for doing Collider HEP style analysis with columnar operations at Fermilab
Home-page: https://github.com/CoffeaTeam/fnal-column-analysis-tools
Author: Lindsey Gray (Fermilab)
Author-email: lagray@fnal.gov
Maintainer: Lindsey Gray (Fermilab)
Maintainer-email: lagray@fnal.gov
License: BSD 3-clause
Download-URL: https://github.com/CoffeaTeam/fnal-column-analysis-tools/releases
Platform: Any
Classifier: Development Status :: 4 - Beta
Classifier: Intended Audience :: Developers
Classifier: Intended Audience :: Information Technology
Classifier: Intended Audience :: Science/Research
Classifier: License :: OSI Approved :: BSD License
Classifier: Operating System :: MacOS
Classifier: Operating System :: POSIX
Classifier: Operating System :: Unix
Classifier: Programming Language :: Python
Classifier: Programming Language :: Python :: 2.7
Classifier: Programming Language :: Python :: 3.6
Classifier: Programming Language :: Python :: 3.7
Classifier: Topic :: Scientific/Engineering
Classifier: Topic :: Scientific/Engineering :: Information Analysis
Classifier: Topic :: Scientific/Engineering :: Mathematics
Classifier: Topic :: Scientific/Engineering :: Physics
Classifier: Topic :: Software Development
Classifier: Topic :: Utilities
Requires-Dist: awkward (>=0.8.4)
Requires-Dist: matplotlib (>=3)
Requires-Dist: numba (>=0.43.1)
Requires-Dist: numpy (>=1.16.0)
Requires-Dist: scipy (>=1.1.0)
Requires-Dist: uproot-methods (>=0.4.3)
Requires-Dist: uproot (>=3.4.5)
Requires-Dist: tqdm
Requires-Dist: futures ; python_version == "2.7"
Provides-Extra: parsl
Requires-Dist: parsl (>=0.7.2) ; extra == 'parsl'
Requires-Dist: cloudpickle ; extra == 'parsl'
Requires-Dist: lz4 ; extra == 'parsl'
Provides-Extra: spark
Requires-Dist: pyspark (>=2.4.1) ; extra == 'spark'
Requires-Dist: pyarrow ; extra == 'spark'
Requires-Dist: cloudpickle ; extra == 'spark'
Requires-Dist: lz4 ; extra == 'spark'
Requires-Dist: jinja2 ; extra == 'spark'
Requires-Dist: pandas ; extra == 'spark'
